README.md
setup.cfg
setup.py
code128agen/__init__.py
code128agen.egg-info/PKG-INFO
code128agen.egg-info/SOURCES.txt
code128agen.egg-info/dependency_links.txt
code128agen.egg-info/requires.txt
code128agen.egg-info/top_level.txt