Metadata-Version: 2.1
Name: code128agen
Version: 0.0.1
Summary: Generation of the Code128a barcode
Home-page: https://github.com/damiandennis/code128agen
Author: Damian Dennis
Author-email: damiandennis@gmail.com
License: UNKNOWN
Platform: UNKNOWN
Requires-Python: >=3.6
